Fibonacci/__init__.py
Fibonacci/fib.py
Linklist/__init__.py
Linklist/common.py
Linklist/tests.py
Map/__init__.py
Map/common.py
Tree/__init__.py
Tree/common.py
data_structure-0.1.1.dist-info/METADATA
data_structure-0.1.1.dist-info/WHEEL
data_structure-0.1.1.dist-info/top_level.txt
data_structure-0.1.1.dist-info/RECORD
