Metadata-Version: 2.1
Name: data-structure
Version: 0.1.1
Summary: for students easy use data-structure.
Home-page: https://github.com/SunHao23333/data-structure/
Author: Oven SUN
Author-email: hao_sun@yeah.net
License: MIT
Platform: UNKNOWN
Classifier: License :: OSI Approved :: MIT License
Classifier: Programming Language :: Python
Classifier: Programming Language :: Python :: 3
Classifier: Programming Language :: Python :: 3.6
Classifier: Programming Language :: Python :: Implementation :: CPython
Classifier: Programming Language :: Python :: Implementation :: PyPy
Requires-Python: >=3.6.0
